<annotation>
	<folder>Images</folder>
	<filename>204.png</filename>
	<path>D:\Desarrollos\labelImg-master\Images\204.png</path>
	<source>
		<database>Unknown</database>
	</source>
	<size>
		<width>224</width>
		<height>224</height>
		<depth>3</depth>
	</size>
	<segmented>0</segmented>
	<object>
		<name>left</name>
		<pose>Unspecified</pose>
		<truncated>0</truncated>
		<difficult>0</difficult>
		<bndbox>
			<xmin>145</xmin>
			<ymin>110</ymin>
			<xmax>203</xmax>
			<ymax>177</ymax>
		</bndbox>
	</object>
</annotation>
